neosensory_python/__init__.py
neosensory_python/__version__.py
neosensory_python-0.0.1.dist-info/LICENSE
neosensory_python-0.0.1.dist-info/METADATA
neosensory_python-0.0.1.dist-info/WHEEL
neosensory_python-0.0.1.dist-info/top_level.txt
neosensory_python-0.0.1.dist-info/RECORD
