Metadata-Version: 2.1
Name: neosensory-python
Version: 0.0.1
Summary: A package to help developers interact with Neosensory products
Home-page: https://github.com/neosensory/neosensory-sdk-for-python
Author: Scott Novich
Author-email: novich@neosensory.com
License: UNKNOWN
Platform: UNKNOWN
Classifier: Development Status :: 1 - Planning
Classifier: License :: OSI Approved :: Apache Software License
Classifier: Operating System :: Microsoft :: Windows :: Windows 10
Classifier: Programming Language :: Python
Classifier: Programming Language :: Python :: 3.6
Classifier: Programming Language :: Python :: 3.7
Classifier: Programming Language :: Python :: 3.8
Requires-Python: >=3.6
Requires-Dist: bleak
